daselement_api/__init__.py
daselement_api/_version.py
daselement_api/api.py
daselement_api/manager.py
daselement_api-1.1.2.dist-info/licenses/LICENSE
daselement_api-1.1.2.dist-info/METADATA
daselement_api-1.1.2.dist-info/WHEEL
daselement_api-1.1.2.dist-info/top_level.txt
daselement_api-1.1.2.dist-info/RECORD
