Metadata-Version: 2.4
Name: daselement-api
Version: 1.1.2
Summary: Das Element Python API
Author-email: Das Element <tech@das-element.com>
Maintainer-email: Das Element <tech@das-element.com>
License-Expression: MIT
Project-URL: Homepage, https://github.com/das-element/python-api
Project-URL: Repository, https://github.com/das-element/python-api
Project-URL: Documentation, http://docu.api.das-element.com
Project-URL: Bug Reports, http://support.das-element.com
Keywords: das-element,api,asset-management
Classifier: Development Status :: 5 - Production/Stable
Classifier: Intended Audience :: Developers
Classifier: Operating System :: OS Independent
Classifier: Programming Language :: Python
Classifier: Programming Language :: Python :: 2
Classifier: Programming Language :: Python :: 2.7
Classifier: Programming Language :: Python :: 3
Classifier: Programming Language :: Python :: 3.6
Classifier: Programming Language :: Python :: 3.7
Classifier: Programming Language :: Python :: 3.8
Classifier: Programming Language :: Python :: 3.9
Classifier: Programming Language :: Python :: 3.10
Classifier: Programming Language :: Python :: 3.11
Classifier: Programming Language :: Python :: 3.12
Requires-Python: >=2.7
License-File: LICENSE
Dynamic: license-file
